{
    "1": "    def js_to_json(code):\n        COMMENT_RE = r'/\\*(?:(?!\\*/).)*?\\*/|//[^\\n]*'\n        SKIP_RE = r'\\s*(?:{comment})?\\s*'.format(comment=COMMENT_RE)\n        INTEGER_TABLE = (\n            (r'(?s)^(0[xX][0-9a-fA-F]+){skip}:?$'.format(skip=SKIP_RE), 16),\n            (r'(?s)^(0+[0-7]+){skip}:?$'.format(skip=SKIP_RE), 8),\n        )\n    \n        def fix_kv(m):\n            v = m.group(0)\n            if v in ('true', 'false', 'null'):\n                return v\n            elif v.startswith('/*') or v.startswith('//') or v == ',':\n                return \"\"\n    \n            if v[0] in (\"'\", '\"'):\n                v = re.sub(r'(?s)\\\\.|\"', lambda m: {\n                    '\"': '\\\\\"',\n                    \"\\\\'\": \"'\",\n                    '\\\\\\n': '',\n                    '\\\\x': '\\\\u00',\n                }.get(m.group(0), m.group(0)), v[1:-1])\n    \n            for regex, base in INTEGER_TABLE:\n                im = re.match(regex, v)\n                if im:\n                    i = int(im.group(1), base)\n                    return '\"%d\":' % i if v.endswith(':') else '%d' % i\n    \n            return '\"%s\"' % v\n    \n        return re.sub(r'''(?sx)\n            \"(?:[^\"\\\\]*(?:\\\\\\\\|\\\\['\"nurtbfx/\\n]))*[^\"\\\\]*\"|\n            '(?:[^'\\\\]*(?:\\\\\\\\|\\\\['\"nurtbfx/\\n]))*[^'\\\\]*'|\n            {comment}|,(?={skip}[\\]}}])|\n            [a-zA-Z_][.a-zA-Z_0-9]*|\n            \\b(?:0[xX][0-9a-fA-F]+|0+[0-7]+)(?:{skip}:)?|\n            [0-9]+(?={skip}:)\n            '''.format(comment=COMMENT_RE, skip=SKIP_RE), fix_kv, code)\n    \n",
    "2": "",
    "3": "# file name: /Volumes/SSD2T/bgp_envs/repos/youtube-dl_15/youtube_dl/utils.py\n\n# relative function's signature in this file\ndef fix_kv(m):\n    # ... omitted code ...\n    pass\n\n",
    "4": "# A test function for the buggy function\n```python\n# file name: /Volumes/SSD2T/bgp_envs/repos/youtube-dl_15/test/test_utils.py\n\n    def test_js_to_json_realworld(self):\n        inp = '''{\n            'clip':{'provider':'pseudo'}\n        }'''\n        self.assertEqual(js_to_json(inp), '''{\n            \"clip\":{\"provider\":\"pseudo\"}\n        }''')\n        json.loads(js_to_json(inp))\n\n        inp = '''{\n            'playlist':[{'controls':{'all':null}}]\n        }'''\n        self.assertEqual(js_to_json(inp), '''{\n            \"playlist\":[{\"controls\":{\"all\":null}}]\n        }''')\n\n        inp = '''\"The CW\\\\'s \\\\'Crazy Ex-Girlfriend\\\\'\"'''\n        self.assertEqual(js_to_json(inp), '''\"The CW's 'Crazy Ex-Girlfriend'\"''')\n\n        inp = '\"SAND Number: SAND 2013-7800P\\\\nPresenter: Tom Russo\\\\nHabanero Software Training - Xyce Software\\\\nXyce, Sandia\\\\u0027s\"'\n        json_code = js_to_json(inp)\n        self.assertEqual(json.loads(json_code), json.loads(inp))\n\n        inp = '''{\n            0:{src:'skipped', type: 'application/dash+xml'},\n            1:{src:'skipped', type: 'application/vnd.apple.mpegURL'},\n        }'''\n        self.assertEqual(js_to_json(inp), '''{\n            \"0\":{\"src\":\"skipped\", \"type\": \"application/dash+xml\"},\n            \"1\":{\"src\":\"skipped\", \"type\": \"application/vnd.apple.mpegURL\"}\n        }''')\n\n        inp = '''{\"foo\":101}'''\n        self.assertEqual(js_to_json(inp), '''{\"foo\":101}''')\n\n        inp = '''{\"duration\": \"00:01:07\"}'''\n        self.assertEqual(js_to_json(inp), '''{\"duration\": \"00:01:07\"}''')\n\n        inp = '''{segments: [{\"offset\":-3.885780586188048e-16,\"duration\":39.75000000000001}]}'''\n        self.assertEqual(js_to_json(inp), '''{\"segments\": [{\"offset\":-3.885780586188048e-16,\"duration\":39.75000000000001}]}''')\n```\n\n## Error message from test function\n```text\nself = <test.test_utils.TestUtil testMethod=test_js_to_json_realworld>\n\n    def test_js_to_json_realworld(self):\n        inp = '''{\n            'clip':{'provider':'pseudo'}\n        }'''\n        self.assertEqual(js_to_json(inp), '''{\n            \"clip\":{\"provider\":\"pseudo\"}\n        }''')\n        json.loads(js_to_json(inp))\n    \n        inp = '''{\n            'playlist':[{'controls':{'all':null}}]\n        }'''\n        self.assertEqual(js_to_json(inp), '''{\n            \"playlist\":[{\"controls\":{\"all\":null}}]\n        }''')\n    \n        inp = '''\"The CW\\\\'s \\\\'Crazy Ex-Girlfriend\\\\'\"'''\n        self.assertEqual(js_to_json(inp), '''\"The CW's 'Crazy Ex-Girlfriend'\"''')\n    \n        inp = '\"SAND Number: SAND 2013-7800P\\\\nPresenter: Tom Russo\\\\nHabanero Software Training - Xyce Software\\\\nXyce, Sandia\\\\u0027s\"'\n        json_code = js_to_json(inp)\n        self.assertEqual(json.loads(json_code), json.loads(inp))\n    \n        inp = '''{\n            0:{src:'skipped', type: 'application/dash+xml'},\n            1:{src:'skipped', type: 'application/vnd.apple.mpegURL'},\n        }'''\n        self.assertEqual(js_to_json(inp), '''{\n            \"0\":{\"src\":\"skipped\", \"type\": \"application/dash+xml\"},\n            \"1\":{\"src\":\"skipped\", \"type\": \"application/vnd.apple.mpegURL\"}\n        }''')\n    \n        inp = '''{\"foo\":101}'''\n        self.assertEqual(js_to_json(inp), '''{\"foo\":101}''')\n    \n        inp = '''{\"duration\": \"00:01:07\"}'''\n        self.assertEqual(js_to_json(inp), '''{\"duration\": \"00:01:07\"}''')\n    \n        inp = '''{segments: [{\"offset\":-3.885780586188048e-16,\"duration\":39.75000000000001}]}'''\n>       self.assertEqual(js_to_json(inp), '''{\"segments\": [{\"offset\":-3.885780586188048e-16,\"duration\":39.75000000000001}]}''')\nE       AssertionError: '{\"se[14 chars]fset\":-3.885780586188048\"e\"-16,\"duration\":39.75000000000001}]}' != '{\"se[14 chars]fset\":-3.885780586188048e-16,\"duration\":39.75000000000001}]}'\nE       - {\"segments\": [{\"offset\":-3.885780586188048\"e\"-16,\"duration\":39.75000000000001}]}\nE       ?                                           - -\nE       + {\"segments\": [{\"offset\":-3.885780586188048e-16,\"duration\":39.75000000000001}]}\n\ntest/test_utils.py:818: AssertionError\n\n```\n",
    "5": "# Variable runtime value and type inside buggy function\n## Buggy case 1\n### input parameter runtime value and type for buggy function\ncode, value: `\"{\\n            'clip':{'provider':'pseudo'}\\n        }\"`, type: `str`\n\n### variable runtime value and type before buggy function return\nCOMMENT_RE, value: `'/\\\\*(?:(?!\\\\*/).)*?\\\\*/`, type: `str`\n\nSKIP_RE, value: `'\\\\s*(?:/\\\\*(?:(?!\\\\*/).)*?\\\\*/`, type: `str`\n\nINTEGER_TABLE, value: `(('(?s)^(0[xX][0-9a-fA-F]+)\\\\s*(?:/\\\\*(?:(?!\\\\*/).)*?\\\\*/`, type: `tuple`\n\nfix_kv, value: `<function js_to_json.<locals>.fix_kv at 0x111eb5c20>`, type: `function`\n\n## Buggy case 2\n### input parameter runtime value and type for buggy function\ncode, value: `\"{\\n            'playlist':[{'controls':{'all':null}}]\\n        }\"`, type: `str`\n\n### variable runtime value and type before buggy function return\nCOMMENT_RE, value: `'/\\\\*(?:(?!\\\\*/).)*?\\\\*/`, type: `str`\n\nSKIP_RE, value: `'\\\\s*(?:/\\\\*(?:(?!\\\\*/).)*?\\\\*/`, type: `str`\n\nINTEGER_TABLE, value: `(('(?s)^(0[xX][0-9a-fA-F]+)\\\\s*(?:/\\\\*(?:(?!\\\\*/).)*?\\\\*/`, type: `tuple`\n\nfix_kv, value: `<function js_to_json.<locals>.fix_kv at 0x111f1d9e0>`, type: `function`\n\n## Buggy case 3\n### input parameter runtime value and type for buggy function\ncode, value: `'\"The CW\\\\\\'s \\\\\\'Crazy Ex-Girlfriend\\\\\\'\"'`, type: `str`\n\n### variable runtime value and type before buggy function return\nCOMMENT_RE, value: `'/\\\\*(?:(?!\\\\*/).)*?\\\\*/`, type: `str`\n\nSKIP_RE, value: `'\\\\s*(?:/\\\\*(?:(?!\\\\*/).)*?\\\\*/`, type: `str`\n\nINTEGER_TABLE, value: `(('(?s)^(0[xX][0-9a-fA-F]+)\\\\s*(?:/\\\\*(?:(?!\\\\*/).)*?\\\\*/`, type: `tuple`\n\nfix_kv, value: `<function js_to_json.<locals>.fix_kv at 0x111eb5b00>`, type: `function`\n\n## Buggy case 4\n### input parameter runtime value and type for buggy function\ncode, value: `'\"SAND Number: SAND 2013-7800P\\\\nPresenter: Tom Russo\\\\nHabanero Software Training - Xyce Software\\\\nXyce, Sandia\\\\u0027s\"'`, type: `str`\n\n### variable runtime value and type before buggy function return\nCOMMENT_RE, value: `'/\\\\*(?:(?!\\\\*/).)*?\\\\*/`, type: `str`\n\nSKIP_RE, value: `'\\\\s*(?:/\\\\*(?:(?!\\\\*/).)*?\\\\*/`, type: `str`\n\nINTEGER_TABLE, value: `(('(?s)^(0[xX][0-9a-fA-F]+)\\\\s*(?:/\\\\*(?:(?!\\\\*/).)*?\\\\*/`, type: `tuple`\n\nfix_kv, value: `<function js_to_json.<locals>.fix_kv at 0x111f1d680>`, type: `function`\n\n## Buggy case 5\n### input parameter runtime value and type for buggy function\ncode, value: `\"{\\n            0:{src:'skipped', type: 'application/dash+xml'},\\n            1:{src:'skipped', type: 'application/vnd.apple.mpegURL'},\\n        }\"`, type: `str`\n\n### variable runtime value and type before buggy function return\nCOMMENT_RE, value: `'/\\\\*(?:(?!\\\\*/).)*?\\\\*/`, type: `str`\n\nSKIP_RE, value: `'\\\\s*(?:/\\\\*(?:(?!\\\\*/).)*?\\\\*/`, type: `str`\n\nINTEGER_TABLE, value: `(('(?s)^(0[xX][0-9a-fA-F]+)\\\\s*(?:/\\\\*(?:(?!\\\\*/).)*?\\\\*/`, type: `tuple`\n\nfix_kv, value: `<function js_to_json.<locals>.fix_kv at 0x111f1d200>`, type: `function`\n\n## Buggy case 6\n### input parameter runtime value and type for buggy function\ncode, value: `'{\"foo\":101}'`, type: `str`\n\n### variable runtime value and type before buggy function return\nCOMMENT_RE, value: `'/\\\\*(?:(?!\\\\*/).)*?\\\\*/`, type: `str`\n\nSKIP_RE, value: `'\\\\s*(?:/\\\\*(?:(?!\\\\*/).)*?\\\\*/`, type: `str`\n\nINTEGER_TABLE, value: `(('(?s)^(0[xX][0-9a-fA-F]+)\\\\s*(?:/\\\\*(?:(?!\\\\*/).)*?\\\\*/`, type: `tuple`\n\nfix_kv, value: `<function js_to_json.<locals>.fix_kv at 0x111f31c20>`, type: `function`\n\n## Buggy case 7\n### input parameter runtime value and type for buggy function\ncode, value: `'{\"duration\": \"00:01:07\"}'`, type: `str`\n\n### variable runtime value and type before buggy function return\nCOMMENT_RE, value: `'/\\\\*(?:(?!\\\\*/).)*?\\\\*/`, type: `str`\n\nSKIP_RE, value: `'\\\\s*(?:/\\\\*(?:(?!\\\\*/).)*?\\\\*/`, type: `str`\n\nINTEGER_TABLE, value: `(('(?s)^(0[xX][0-9a-fA-F]+)\\\\s*(?:/\\\\*(?:(?!\\\\*/).)*?\\\\*/`, type: `tuple`\n\nfix_kv, value: `<function js_to_json.<locals>.fix_kv at 0x111f1dd40>`, type: `function`\n\n## Buggy case 8\n### input parameter runtime value and type for buggy function\ncode, value: `'{segments: [{\"offset\":-3.885780586188048e-16,\"duration\":39.75000000000001}]}'`, type: `str`\n\n### variable runtime value and type before buggy function return\nCOMMENT_RE, value: `'/\\\\*(?:(?!\\\\*/).)*?\\\\*/`, type: `str`\n\nSKIP_RE, value: `'\\\\s*(?:/\\\\*(?:(?!\\\\*/).)*?\\\\*/`, type: `str`\n\nINTEGER_TABLE, value: `(('(?s)^(0[xX][0-9a-fA-F]+)\\\\s*(?:/\\\\*(?:(?!\\\\*/).)*?\\\\*/`, type: `tuple`\n\nfix_kv, value: `<function js_to_json.<locals>.fix_kv at 0x111f1d200>`, type: `function`\n\n\n\n# Expected variable value and type in tests\n## Expected case 1\n### Input parameter value and type\ncode, value: `\"{\\n            'clip':{'provider':'pseudo'}\\n        }\"`, type: `str`\n\n### Expected variable value and type before function return\nCOMMENT_RE, expected value: `'/\\\\*(?:(?!\\\\*/).)*?\\\\*/`, type: `str`\n\nSKIP_RE, expected value: `'\\\\s*(?:/\\\\*(?:(?!\\\\*/).)*?\\\\*/`, type: `str`\n\nINTEGER_TABLE, expected value: `(('(?s)^(0[xX][0-9a-fA-F]+)\\\\s*(?:/\\\\*(?:(?!\\\\*/).)*?\\\\*/`, type: `tuple`\n\nfix_kv, expected value: `<function js_to_json.<locals>.fix_kv at 0x10708ec20>`, type: `function`\n\n## Expected case 2\n### Input parameter value and type\ncode, value: `\"{\\n            'playlist':[{'controls':{'all':null}}]\\n        }\"`, type: `str`\n\n### Expected variable value and type before function return\nCOMMENT_RE, expected value: `'/\\\\*(?:(?!\\\\*/).)*?\\\\*/`, type: `str`\n\nSKIP_RE, expected value: `'\\\\s*(?:/\\\\*(?:(?!\\\\*/).)*?\\\\*/`, type: `str`\n\nINTEGER_TABLE, expected value: `(('(?s)^(0[xX][0-9a-fA-F]+)\\\\s*(?:/\\\\*(?:(?!\\\\*/).)*?\\\\*/`, type: `tuple`\n\nfix_kv, expected value: `<function js_to_json.<locals>.fix_kv at 0x1070f0050>`, type: `function`\n\n## Expected case 3\n### Input parameter value and type\ncode, value: `'\"The CW\\\\\\'s \\\\\\'Crazy Ex-Girlfriend\\\\\\'\"'`, type: `str`\n\n### Expected variable value and type before function return\nCOMMENT_RE, expected value: `'/\\\\*(?:(?!\\\\*/).)*?\\\\*/`, type: `str`\n\nSKIP_RE, expected value: `'\\\\s*(?:/\\\\*(?:(?!\\\\*/).)*?\\\\*/`, type: `str`\n\nINTEGER_TABLE, expected value: `(('(?s)^(0[xX][0-9a-fA-F]+)\\\\s*(?:/\\\\*(?:(?!\\\\*/).)*?\\\\*/`, type: `tuple`\n\nfix_kv, expected value: `<function js_to_json.<locals>.fix_kv at 0x1070f6290>`, type: `function`\n\n## Expected case 4\n### Input parameter value and type\ncode, value: `'\"SAND Number: SAND 2013-7800P\\\\nPresenter: Tom Russo\\\\nHabanero Software Training - Xyce Software\\\\nXyce, Sandia\\\\u0027s\"'`, type: `str`\n\n### Expected variable value and type before function return\nCOMMENT_RE, expected value: `'/\\\\*(?:(?!\\\\*/).)*?\\\\*/`, type: `str`\n\nSKIP_RE, expected value: `'\\\\s*(?:/\\\\*(?:(?!\\\\*/).)*?\\\\*/`, type: `str`\n\nINTEGER_TABLE, expected value: `(('(?s)^(0[xX][0-9a-fA-F]+)\\\\s*(?:/\\\\*(?:(?!\\\\*/).)*?\\\\*/`, type: `tuple`\n\nfix_kv, expected value: `<function js_to_json.<locals>.fix_kv at 0x107108440>`, type: `function`\n\n## Expected case 5\n### Input parameter value and type\ncode, value: `\"{\\n            0:{src:'skipped', type: 'application/dash+xml'},\\n            1:{src:'skipped', type: 'application/vnd.apple.mpegURL'},\\n        }\"`, type: `str`\n\n### Expected variable value and type before function return\nCOMMENT_RE, expected value: `'/\\\\*(?:(?!\\\\*/).)*?\\\\*/`, type: `str`\n\nSKIP_RE, expected value: `'\\\\s*(?:/\\\\*(?:(?!\\\\*/).)*?\\\\*/`, type: `str`\n\nINTEGER_TABLE, expected value: `(('(?s)^(0[xX][0-9a-fA-F]+)\\\\s*(?:/\\\\*(?:(?!\\\\*/).)*?\\\\*/`, type: `tuple`\n\nfix_kv, expected value: `<function js_to_json.<locals>.fix_kv at 0x1070f0170>`, type: `function`\n\n## Expected case 6\n### Input parameter value and type\ncode, value: `'{\"foo\":101}'`, type: `str`\n\n### Expected variable value and type before function return\nCOMMENT_RE, expected value: `'/\\\\*(?:(?!\\\\*/).)*?\\\\*/`, type: `str`\n\nSKIP_RE, expected value: `'\\\\s*(?:/\\\\*(?:(?!\\\\*/).)*?\\\\*/`, type: `str`\n\nINTEGER_TABLE, expected value: `(('(?s)^(0[xX][0-9a-fA-F]+)\\\\s*(?:/\\\\*(?:(?!\\\\*/).)*?\\\\*/`, type: `tuple`\n\nfix_kv, expected value: `<function js_to_json.<locals>.fix_kv at 0x1070f0ef0>`, type: `function`\n\n## Expected case 7\n### Input parameter value and type\ncode, value: `'{\"duration\": \"00:01:07\"}'`, type: `str`\n\n### Expected variable value and type before function return\nCOMMENT_RE, expected value: `'/\\\\*(?:(?!\\\\*/).)*?\\\\*/`, type: `str`\n\nSKIP_RE, expected value: `'\\\\s*(?:/\\\\*(?:(?!\\\\*/).)*?\\\\*/`, type: `str`\n\nINTEGER_TABLE, expected value: `(('(?s)^(0[xX][0-9a-fA-F]+)\\\\s*(?:/\\\\*(?:(?!\\\\*/).)*?\\\\*/`, type: `tuple`\n\nfix_kv, expected value: `<function js_to_json.<locals>.fix_kv at 0x1070f0290>`, type: `function`\n\n## Expected case 8\n### Input parameter value and type\ncode, value: `'{segments: [{\"offset\":-3.885780586188048e-16,\"duration\":39.75000000000001}]}'`, type: `str`\n\n### Expected variable value and type before function return\nCOMMENT_RE, expected value: `'/\\\\*(?:(?!\\\\*/).)*?\\\\*/`, type: `str`\n\nSKIP_RE, expected value: `'\\\\s*(?:/\\\\*(?:(?!\\\\*/).)*?\\\\*/`, type: `str`\n\nINTEGER_TABLE, expected value: `(('(?s)^(0[xX][0-9a-fA-F]+)\\\\s*(?:/\\\\*(?:(?!\\\\*/).)*?\\\\*/`, type: `tuple`\n\nfix_kv, expected value: `<function js_to_json.<locals>.fix_kv at 0x10708ee60>`, type: `function`\n\n\n\n",
    "6": "# A GitHub issue title for this bug\n```text\n[utils] js_to_json can't handle scientific notations (was: [twitch:clips] JSONDecodeError for certain clips)\n```\n\n## The associated detailed issue description\n```text\n I've verified and I assure that I'm running youtube-dl 2017.11.15\nBefore submitting an issue make sure you have:\n At least skimmed through the README, most notably the FAQ and BUGS sections\n Searched the bugtracker for similar issues including closed ones\nWhat is the purpose of your issue?\n Bug report (encountered problems with youtube-dl)\n Site support request (request for adding support for a new site)\n Feature request (request for a new functionality)\n Question\n Other\nThe following sections concretize particular purposed issues, you can erase any section (the contents between triple ---) not applicable to your issue\nIf the purpose of this issue is a bug report, site support request or you are not completely sure provide the full verbose output as follows:\nAdd the -v flag to your command line you run youtube-dl with (youtube-dl -v <your command line>), copy the whole output and insert it here. It should look similar to one below (replace it with your log inserted between triple ```\n\n",
    "7": "# Instructions\n\n1. Analyze the test case and its relationship with the error message, if applicable.\n2. Identify the potential error location within the problematic function.\n3. Explain the reasons behind the occurrence of the bug.\n4. Suggest possible approaches for fixing the bug.\n5. Present the corrected code for the problematic function."
}