{
    "pandas": [
        {
            "bugID": 126,
            "bitvector": {
                "1.1.1": 1,
                "1.1.2": 1,
                "1.2.1": 0,
                "1.2.2": 0,
                "1.2.3": 0,
                "1.3.1": 0,
                "1.3.2": 0,
                "1.4.1": 0,
                "1.4.2": 0,
                "2.1.1": 0,
                "2.1.2": 0,
                "2.1.3": 0,
                "2.1.4": 0,
                "2.1.5": 0,
                "2.1.6": 0,
                "3.1.1": 0,
                "3.1.2": 0,
                "cot": 1
            },
            "strata": {
                "1": 1,
                "2": 0,
                "3": 0,
                "4": 0,
                "5": 0,
                "6": 0,
                "7": 1
            },
            "available_bitvector": {
                "1.1.1": 1,
                "1.1.2": 1,
                "1.2.1": 0,
                "1.2.2": 0,
                "1.2.3": 0,
                "1.3.1": 0,
                "1.3.2": 0,
                "1.4.1": 0,
                "1.4.2": 0,
                "2.1.1": 0,
                "2.1.2": 0,
                "2.1.3": 0,
                "2.1.4": 0,
                "2.1.5": 0,
                "2.1.6": 0,
                "3.1.1": 0,
                "3.1.2": 0,
                "cot": 1
            },
            "available_strata": {
                "1": 1,
                "2": 0,
                "3": 0,
                "4": 0,
                "5": 0,
                "6": 0,
                "7": 1
            },
            "start_line": 6822,
            "file_name": "pandas/core/frame.py",
            "replace_code": "def append(self, other, ignore_index=False, verify_integrity=False, sort=None):\n    import pandas as pd\n    import pandas as pd\n    \n    if isinstance(other, (pd.Series, dict)):\n        if isinstance(other, dict):\n            other = pd.Series(other)\n        if other.name is None and not ignore_index:\n            raise TypeError(\n                \"Can only append a Series if ignore_index=True or if the Series has a name\"\n            )\n    \n        # Reindex the other Series to match the columns of self\n        other = other.reindex(self.columns, copy=False)\n        other = pd.DataFrame(other).T\n    elif isinstance(other, list) and not isinstance(other[0], pd.DataFrame):\n        # Convert list to DataFrame and match the columns of self\n        other = pd.DataFrame(other, columns=self.columns)\n    else:\n        # Convert other DataFrame to match the columns of self\n        other = other.reindex(columns=self.columns)\n    \n    return pd.concat([self, other], ignore_index=ignore_index, sort=sort)"
        }
    ]
}