{
    "pandas": [
        {
            "bitvector": {
                "1.1.1": 1,
                "1.1.2": 1,
                "1.3.1": 0,
                "1.3.2": 0,
                "1.4.1": 1,
                "1.2.1": 1,
                "1.4.2": 1,
                "1.2.2": 1,
                "1.5.1": 1,
                "1.5.2": 1,
                "2.1.1": 0,
                "2.1.2": 0,
                "2.2.1": 0,
                "2.2.2": 0,
                "2.3.1": 0,
                "2.3.2": 0,
                "3.1.1": 1,
                "3.1.2": 1,
                "cot": 1
            },
            "strata": {
                "1": 1,
                "2": 0,
                "3": 1,
                "4": 1,
                "5": 0,
                "6": 0,
                "7": 0,
                "8": 1,
                "9": 1
            },
            "available_bitvector": {
                "1.1.1": 1,
                "1.1.2": 1,
                "1.3.1": 0,
                "1.3.2": 0,
                "1.4.1": 0,
                "1.2.1": 1,
                "1.4.2": 1,
                "1.2.2": 1,
                "1.5.1": 1,
                "1.5.2": 1,
                "2.1.1": 0,
                "2.1.2": 0,
                "2.2.1": 0,
                "2.2.2": 0,
                "2.3.1": 0,
                "2.3.2": 0,
                "3.1.1": 1,
                "3.1.2": 1,
                "cot": 1
            },
            "available_strata": {
                "1": 1,
                "2": 0,
                "3": 1,
                "4": 1,
                "5": 0,
                "6": 0,
                "7": 0,
                "8": 1,
                "9": 1
            },
            "bugID": 168,
            "start_line": 425,
            "file_name": "pandas/core/groupby/grouper.py",
            "replace_code": "def _get_grouper(\n    obj,\n    key=None,\n    axis=0,\n    level=None,\n    sort=True,\n    observed=False,\n    mutated=False,\n    validate=True,\n):\n    group_axis = obj._get_axis(axis)\n\n    if key is not None:\n        # Check if key is a valid column name for grouping\n        if key in obj.columns:\n            gpr = key\n            index_level = None\n            in_axis = True\n            exclusions = [key]\n        else:\n            raise KeyError(key)\n    else:\n        # No key provided, group by default axis (columns)\n        gpr = obj.columns\n        index_level = None\n        in_axis = True\n        exclusions = list(obj.columns)\n\n    # create the Grouping\n    ping = Grouping(\n        group_axis,\n        gpr,\n        obj=obj,\n        name=group_axis.name,\n        level=index_level,\n        sort=sort,\n        observed=observed,\n        in_axis=in_axis,\n    )\n\n    # Prepare the BaseGrouper and return\n    grouper = BaseGrouper(group_axis, [ping], sort=sort, mutated=mutated)\n    return grouper, exclusions, obj",
            "import_list": []
        }
    ]
}