{
    "pandas": [
        {
            "bitvector": {
                "1.1.1": 1,
                "1.1.2": 1,
                "1.2.1": 0,
                "1.2.2": 0,
                "1.2.3": 0,
                "1.3.1": 1,
                "1.3.2": 0,
                "1.3.3": 1,
                "1.4.1": 0,
                "1.4.2": 0,
                "2.1.1": 0,
                "2.1.2": 0,
                "2.1.5": 0,
                "2.1.6": 0,
                "2.1.3": 0,
                "2.1.4": 0,
                "3.1.1": 1,
                "3.1.2": 1,
                "cot": 1
            },
            "strata": {
                "1": 1,
                "2": 0,
                "3": 0,
                "4": 0,
                "5": 0,
                "6": 0,
                "7": 0,
                "8": 1,
                "9": 1
            },
            "available_bitvector": {
                "1.1.1": 1,
                "1.1.2": 1,
                "1.2.1": 0,
                "1.2.2": 0,
                "1.2.3": 0,
                "1.3.1": 1,
                "1.3.2": 0,
                "1.3.3": 1,
                "1.4.1": 0,
                "1.4.2": 0,
                "2.1.1": 0,
                "2.1.2": 0,
                "2.1.5": 0,
                "2.1.6": 0,
                "2.1.3": 0,
                "2.1.4": 0,
                "3.1.1": 1,
                "3.1.2": 1,
                "cot": 1
            },
            "available_strata": {
                "1": 1,
                "2": 0,
                "3": 0,
                "4": 0,
                "5": 0,
                "6": 0,
                "7": 0,
                "8": 1,
                "9": 1
            },
            "bugID": 168,
            "start_line": 425,
            "file_name": "pandas/core/groupby/grouper.py",
            "replace_code": "def _get_grouper(\n    obj,\n    key=None,\n    axis=0,\n    level=None,\n    sort=True,\n    observed=False,\n    mutated=False,\n    validate=True,\n):\n    # ... (existing function code)\n\n    # replace the existing function code with the corrected code below\n\n    if axis == 1 and is_list_like(key):\n        group_axis = obj._get_axis(1)\n        keys = key\n        groupings = []\n\n        for key in keys:\n            groupings.append(\n                Grouping(\n                    group_axis,\n                    key,\n                    obj=obj,\n                    name=key,\n                    level=level,\n                    sort=sort,\n                    observed=observed,\n                    in_axis=True,  # indicating it's in the axis\n                )\n            )\n\n        if len(groupings) == 0 and len(obj.columns):\n            raise ValueError(\"No group keys passed!\")\n        elif len(groupings) == 0:\n            groupings.append(\n                Grouping(Index([], dtype=\"int\"), np.array([], dtype=np.intp))\n            )\n\n        grouper = BaseGrouper(group_axis, groupings, sort=sort, mutated=mutated)\n        return grouper, [], obj",
            "import_list": []
        }
    ]
}