{
    "thefuck:9": {
        "/Volumes/SSD2T/bgp_envs_non_pandas/repos/thefuck_9/thefuck/rules/git_push.py": {
            "buggy_functions": [
                {
                    "function_name": "get_new_command",
                    "function_code": "@git_support\ndef get_new_command(command):\n    # If --set-upstream or -u are passed, remove it and its argument. This is\n    # because the remaining arguments are concatenated onto the command suggested\n    # by git, which includes --set-upstream and its argument\n    upstream_option_index = -1\n    try:\n        upstream_option_index = command.script_parts.index('--set-upstream')\n    except ValueError:\n        pass\n    try:\n        upstream_option_index = command.script_parts.index('-u')\n    except ValueError:\n        pass\n    if upstream_option_index is not -1:\n        command.script_parts.pop(upstream_option_index)\n        command.script_parts.pop(upstream_option_index)\n\n    push_upstream = command.stderr.split('\\n')[-3].strip().partition('git ')[2]\n    return replace_argument(\" \".join(command.script_parts), 'push', push_upstream)\n",
                    "decorators": [
                        "git_support"
                    ],
                    "docstring": null,
                    "start_line": 11,
                    "variables": {
                        "upstream_option_index": [
                            16,
                            18,
                            22,
                            25,
                            26,
                            27
                        ],
                        "command.script_parts.index": [
                            18,
                            22
                        ],
                        "command.script_parts": [
                            18,
                            22,
                            26,
                            27,
                            30
                        ],
                        "command": [
                            18,
                            22,
                            26,
                            27,
                            29,
                            30
                        ],
                        "ValueError": [
                            19,
                            23
                        ],
                        "command.script_parts.pop": [
                            26,
                            27
                        ],
                        "push_upstream": [
                            29,
                            30
                        ],
                        "partition": [
                            29
                        ],
                        "strip": [
                            29
                        ],
                        "command.stderr.split": [
                            29
                        ],
                        "command.stderr": [
                            29
                        ],
                        "replace_argument": [
                            30
                        ],
                        "join": [
                            30
                        ],
                        "git_support": [
                            11
                        ]
                    },
                    "filtered_variables": {
                        "upstream_option_index": [
                            16,
                            18,
                            22,
                            25,
                            26,
                            27
                        ],
                        "command.script_parts.index": [
                            18,
                            22
                        ],
                        "command.script_parts": [
                            18,
                            22,
                            26,
                            27,
                            30
                        ],
                        "command": [
                            18,
                            22,
                            26,
                            27,
                            29,
                            30
                        ],
                        "command.script_parts.pop": [
                            26,
                            27
                        ],
                        "push_upstream": [
                            29,
                            30
                        ],
                        "partition": [
                            29
                        ],
                        "strip": [
                            29
                        ],
                        "command.stderr.split": [
                            29
                        ],
                        "command.stderr": [
                            29
                        ],
                        "replace_argument": [
                            30
                        ],
                        "join": [
                            30
                        ],
                        "git_support": [
                            11
                        ]
                    },
                    "diff_line_number": 27,
                    "class_data": null,
                    "variable_values": [
                        [
                            {
                                "upstream_option_index": {
                                    "variable_value": null,
                                    "variable_type": "None",
                                    "variable_shape": null
                                },
                                "command.script_parts.index": {
                                    "variable_value": "None",
                                    "variable_type": "NoneType",
                                    "variable_shape": null
                                },
                                "command.script_parts": {
                                    "variable_value": "['git', 'push']",
                                    "variable_type": "list",
                                    "variable_shape": "2"
                                },
                                "command": {
                                    "variable_value": "Command(script=git push, stdout=, stderr=fatal: The current branch master has no upstream branch.\nTo push the current branch and set the remote as upstream, use\n\n    git push --set-upstream origin master\n\n)",
                                    "variable_type": "Command",
                                    "variable_shape": null
                                },
                                "command.script_parts.pop": {
                                    "variable_value": "None",
                                    "variable_type": "NoneType",
                                    "variable_shape": null
                                },
                                "push_upstream": {
                                    "variable_value": null,
                                    "variable_type": "None",
                                    "variable_shape": null
                                },
                                "partition": {
                                    "variable_value": null,
                                    "variable_type": "None",
                                    "variable_shape": null
                                },
                                "strip": {
                                    "variable_value": null,
                                    "variable_type": "None",
                                    "variable_shape": null
                                },
                                "command.stderr.split": {
                                    "variable_value": "None",
                                    "variable_type": "NoneType",
                                    "variable_shape": null
                                },
                                "command.stderr": {
                                    "variable_value": "'fatal: The current branch master has no upstream branch.\\nTo push the current branch and set the remote as upstream, use\\n\\n    git push --set-upstream origin master\\n\\n'",
                                    "variable_type": "str",
                                    "variable_shape": "164"
                                },
                                "replace_argument": {
                                    "variable_value": null,
                                    "variable_type": "None",
                                    "variable_shape": null
                                },
                                "join": {
                                    "variable_value": null,
                                    "variable_type": "None",
                                    "variable_shape": null
                                },
                                "git_support": {
                                    "variable_value": null,
                                    "variable_type": "None",
                                    "variable_shape": null
                                }
                            },
                            {
                                "upstream_option_index": {
                                    "variable_value": "-1",
                                    "variable_type": "int",
                                    "variable_shape": null
                                },
                                "command.script_parts.index": {
                                    "variable_value": "None",
                                    "variable_type": "NoneType",
                                    "variable_shape": null
                                },
                                "command.script_parts": {
                                    "variable_value": "['git', 'push']",
                                    "variable_type": "list",
                                    "variable_shape": "2"
                                },
                                "command": {
                                    "variable_value": "Command(script=git push, stdout=, stderr=fatal: The current branch master has no upstream branch.\nTo push the current branch and set the remote as upstream, use\n\n    git push --set-upstream origin master\n\n)",
                                    "variable_type": "Command",
                                    "variable_shape": null
                                },
                                "command.script_parts.pop": {
                                    "variable_value": "None",
                                    "variable_type": "NoneType",
                                    "variable_shape": null
                                },
                                "push_upstream": {
                                    "variable_value": "'push --set-upstream origin master'",
                                    "variable_type": "str",
                                    "variable_shape": "33"
                                },
                                "partition": {
                                    "variable_value": null,
                                    "variable_type": "None",
                                    "variable_shape": null
                                },
                                "strip": {
                                    "variable_value": null,
                                    "variable_type": "None",
                                    "variable_shape": null
                                },
                                "command.stderr.split": {
                                    "variable_value": "None",
                                    "variable_type": "NoneType",
                                    "variable_shape": null
                                },
                                "command.stderr": {
                                    "variable_value": "'fatal: The current branch master has no upstream branch.\\nTo push the current branch and set the remote as upstream, use\\n\\n    git push --set-upstream origin master\\n\\n'",
                                    "variable_type": "str",
                                    "variable_shape": "164"
                                },
                                "replace_argument": {
                                    "variable_value": null,
                                    "variable_type": "None",
                                    "variable_shape": null
                                },
                                "join": {
                                    "variable_value": null,
                                    "variable_type": "None",
                                    "variable_shape": null
                                },
                                "git_support": {
                                    "variable_value": null,
                                    "variable_type": "None",
                                    "variable_shape": null
                                }
                            }
                        ]
                    ],
                    "angelic_variable_values": [
                        [
                            {
                                "upstream_option_index": {
                                    "variable_value": null,
                                    "variable_type": "None",
                                    "variable_shape": null
                                },
                                "command.script_parts.index": {
                                    "variable_value": "None",
                                    "variable_type": "NoneType",
                                    "variable_shape": null
                                },
                                "command.script_parts": {
                                    "variable_value": "['git', 'push']",
                                    "variable_type": "list",
                                    "variable_shape": "2"
                                },
                                "command": {
                                    "variable_value": "Command(script=git push, stdout=, stderr=fatal: The current branch master has no upstream branch.\nTo push the current branch and set the remote as upstream, use\n\n    git push --set-upstream origin master\n\n)",
                                    "variable_type": "Command",
                                    "variable_shape": null
                                },
                                "command.script_parts.pop": {
                                    "variable_value": "None",
                                    "variable_type": "NoneType",
                                    "variable_shape": null
                                },
                                "push_upstream": {
                                    "variable_value": null,
                                    "variable_type": "None",
                                    "variable_shape": null
                                },
                                "partition": {
                                    "variable_value": null,
                                    "variable_type": "None",
                                    "variable_shape": null
                                },
                                "strip": {
                                    "variable_value": null,
                                    "variable_type": "None",
                                    "variable_shape": null
                                },
                                "command.stderr.split": {
                                    "variable_value": "None",
                                    "variable_type": "NoneType",
                                    "variable_shape": null
                                },
                                "command.stderr": {
                                    "variable_value": "'fatal: The current branch master has no upstream branch.\\nTo push the current branch and set the remote as upstream, use\\n\\n    git push --set-upstream origin master\\n\\n'",
                                    "variable_type": "str",
                                    "variable_shape": "164"
                                },
                                "replace_argument": {
                                    "variable_value": null,
                                    "variable_type": "None",
                                    "variable_shape": null
                                },
                                "join": {
                                    "variable_value": null,
                                    "variable_type": "None",
                                    "variable_shape": null
                                },
                                "git_support": {
                                    "variable_value": null,
                                    "variable_type": "None",
                                    "variable_shape": null
                                }
                            },
                            {
                                "upstream_option_index": {
                                    "variable_value": "-1",
                                    "variable_type": "int",
                                    "variable_shape": null
                                },
                                "command.script_parts.index": {
                                    "variable_value": "None",
                                    "variable_type": "NoneType",
                                    "variable_shape": null
                                },
                                "command.script_parts": {
                                    "variable_value": "['git', 'push']",
                                    "variable_type": "list",
                                    "variable_shape": "2"
                                },
                                "command": {
                                    "variable_value": "Command(script=git push, stdout=, stderr=fatal: The current branch master has no upstream branch.\nTo push the current branch and set the remote as upstream, use\n\n    git push --set-upstream origin master\n\n)",
                                    "variable_type": "Command",
                                    "variable_shape": null
                                },
                                "command.script_parts.pop": {
                                    "variable_value": "None",
                                    "variable_type": "NoneType",
                                    "variable_shape": null
                                },
                                "push_upstream": {
                                    "variable_value": "'push --set-upstream origin master'",
                                    "variable_type": "str",
                                    "variable_shape": "33"
                                },
                                "partition": {
                                    "variable_value": null,
                                    "variable_type": "None",
                                    "variable_shape": null
                                },
                                "strip": {
                                    "variable_value": null,
                                    "variable_type": "None",
                                    "variable_shape": null
                                },
                                "command.stderr.split": {
                                    "variable_value": "None",
                                    "variable_type": "NoneType",
                                    "variable_shape": null
                                },
                                "command.stderr": {
                                    "variable_value": "'fatal: The current branch master has no upstream branch.\\nTo push the current branch and set the remote as upstream, use\\n\\n    git push --set-upstream origin master\\n\\n'",
                                    "variable_type": "str",
                                    "variable_shape": "164"
                                },
                                "replace_argument": {
                                    "variable_value": null,
                                    "variable_type": "None",
                                    "variable_shape": null
                                },
                                "join": {
                                    "variable_value": null,
                                    "variable_type": "None",
                                    "variable_shape": null
                                },
                                "git_support": {
                                    "variable_value": null,
                                    "variable_type": "None",
                                    "variable_shape": null
                                }
                            }
                        ],
                        [
                            {
                                "upstream_option_index": {
                                    "variable_value": null,
                                    "variable_type": "None",
                                    "variable_shape": null
                                },
                                "command.script_parts.index": {
                                    "variable_value": "None",
                                    "variable_type": "NoneType",
                                    "variable_shape": null
                                },
                                "command.script_parts": {
                                    "variable_value": "['git', 'push', '-u']",
                                    "variable_type": "list",
                                    "variable_shape": "3"
                                },
                                "command": {
                                    "variable_value": "Command(script=git push -u, stdout=, stderr=fatal: The current branch master has no upstream branch.\nTo push the current branch and set the remote as upstream, use\n\n    git push --set-upstream origin master\n\n)",
                                    "variable_type": "Command",
                                    "variable_shape": null
                                },
                                "command.script_parts.pop": {
                                    "variable_value": "None",
                                    "variable_type": "NoneType",
                                    "variable_shape": null
                                },
                                "push_upstream": {
                                    "variable_value": null,
                                    "variable_type": "None",
                                    "variable_shape": null
                                },
                                "partition": {
                                    "variable_value": null,
                                    "variable_type": "None",
                                    "variable_shape": null
                                },
                                "strip": {
                                    "variable_value": null,
                                    "variable_type": "None",
                                    "variable_shape": null
                                },
                                "command.stderr.split": {
                                    "variable_value": "None",
                                    "variable_type": "NoneType",
                                    "variable_shape": null
                                },
                                "command.stderr": {
                                    "variable_value": "'fatal: The current branch master has no upstream branch.\\nTo push the current branch and set the remote as upstream, use\\n\\n    git push --set-upstream origin master\\n\\n'",
                                    "variable_type": "str",
                                    "variable_shape": "164"
                                },
                                "replace_argument": {
                                    "variable_value": null,
                                    "variable_type": "None",
                                    "variable_shape": null
                                },
                                "join": {
                                    "variable_value": null,
                                    "variable_type": "None",
                                    "variable_shape": null
                                },
                                "git_support": {
                                    "variable_value": null,
                                    "variable_type": "None",
                                    "variable_shape": null
                                }
                            },
                            {
                                "upstream_option_index": {
                                    "variable_value": "2",
                                    "variable_type": "int",
                                    "variable_shape": null
                                },
                                "command.script_parts.index": {
                                    "variable_value": "None",
                                    "variable_type": "NoneType",
                                    "variable_shape": null
                                },
                                "command.script_parts": {
                                    "variable_value": "['git', 'push']",
                                    "variable_type": "list",
                                    "variable_shape": "2"
                                },
                                "command": {
                                    "variable_value": "Command(script=git push -u, stdout=, stderr=fatal: The current branch master has no upstream branch.\nTo push the current branch and set the remote as upstream, use\n\n    git push --set-upstream origin master\n\n)",
                                    "variable_type": "Command",
                                    "variable_shape": null
                                },
                                "command.script_parts.pop": {
                                    "variable_value": "None",
                                    "variable_type": "NoneType",
                                    "variable_shape": null
                                },
                                "push_upstream": {
                                    "variable_value": "'push --set-upstream origin master'",
                                    "variable_type": "str",
                                    "variable_shape": "33"
                                },
                                "partition": {
                                    "variable_value": null,
                                    "variable_type": "None",
                                    "variable_shape": null
                                },
                                "strip": {
                                    "variable_value": null,
                                    "variable_type": "None",
                                    "variable_shape": null
                                },
                                "command.stderr.split": {
                                    "variable_value": "None",
                                    "variable_type": "NoneType",
                                    "variable_shape": null
                                },
                                "command.stderr": {
                                    "variable_value": "'fatal: The current branch master has no upstream branch.\\nTo push the current branch and set the remote as upstream, use\\n\\n    git push --set-upstream origin master\\n\\n'",
                                    "variable_type": "str",
                                    "variable_shape": "164"
                                },
                                "replace_argument": {
                                    "variable_value": null,
                                    "variable_type": "None",
                                    "variable_shape": null
                                },
                                "join": {
                                    "variable_value": null,
                                    "variable_type": "None",
                                    "variable_shape": null
                                },
                                "git_support": {
                                    "variable_value": null,
                                    "variable_type": "None",
                                    "variable_shape": null
                                }
                            }
                        ],
                        [
                            {
                                "upstream_option_index": {
                                    "variable_value": null,
                                    "variable_type": "None",
                                    "variable_shape": null
                                },
                                "command.script_parts.index": {
                                    "variable_value": "None",
                                    "variable_type": "NoneType",
                                    "variable_shape": null
                                },
                                "command.script_parts": {
                                    "variable_value": "['git', 'push', '-u', 'origin']",
                                    "variable_type": "list",
                                    "variable_shape": "4"
                                },
                                "command": {
                                    "variable_value": "Command(script=git push -u origin, stdout=, stderr=fatal: The current branch master has no upstream branch.\nTo push the current branch and set the remote as upstream, use\n\n    git push --set-upstream origin master\n\n)",
                                    "variable_type": "Command",
                                    "variable_shape": null
                                },
                                "command.script_parts.pop": {
                                    "variable_value": "None",
                                    "variable_type": "NoneType",
                                    "variable_shape": null
                                },
                                "push_upstream": {
                                    "variable_value": null,
                                    "variable_type": "None",
                                    "variable_shape": null
                                },
                                "partition": {
                                    "variable_value": null,
                                    "variable_type": "None",
                                    "variable_shape": null
                                },
                                "strip": {
                                    "variable_value": null,
                                    "variable_type": "None",
                                    "variable_shape": null
                                },
                                "command.stderr.split": {
                                    "variable_value": "None",
                                    "variable_type": "NoneType",
                                    "variable_shape": null
                                },
                                "command.stderr": {
                                    "variable_value": "'fatal: The current branch master has no upstream branch.\\nTo push the current branch and set the remote as upstream, use\\n\\n    git push --set-upstream origin master\\n\\n'",
                                    "variable_type": "str",
                                    "variable_shape": "164"
                                },
                                "replace_argument": {
                                    "variable_value": null,
                                    "variable_type": "None",
                                    "variable_shape": null
                                },
                                "join": {
                                    "variable_value": null,
                                    "variable_type": "None",
                                    "variable_shape": null
                                },
                                "git_support": {
                                    "variable_value": null,
                                    "variable_type": "None",
                                    "variable_shape": null
                                }
                            },
                            {
                                "upstream_option_index": {
                                    "variable_value": "2",
                                    "variable_type": "int",
                                    "variable_shape": null
                                },
                                "command.script_parts.index": {
                                    "variable_value": "None",
                                    "variable_type": "NoneType",
                                    "variable_shape": null
                                },
                                "command.script_parts": {
                                    "variable_value": "['git', 'push']",
                                    "variable_type": "list",
                                    "variable_shape": "2"
                                },
                                "command": {
                                    "variable_value": "Command(script=git push -u origin, stdout=, stderr=fatal: The current branch master has no upstream branch.\nTo push the current branch and set the remote as upstream, use\n\n    git push --set-upstream origin master\n\n)",
                                    "variable_type": "Command",
                                    "variable_shape": null
                                },
                                "command.script_parts.pop": {
                                    "variable_value": "None",
                                    "variable_type": "NoneType",
                                    "variable_shape": null
                                },
                                "push_upstream": {
                                    "variable_value": "'push --set-upstream origin master'",
                                    "variable_type": "str",
                                    "variable_shape": "33"
                                },
                                "partition": {
                                    "variable_value": null,
                                    "variable_type": "None",
                                    "variable_shape": null
                                },
                                "strip": {
                                    "variable_value": null,
                                    "variable_type": "None",
                                    "variable_shape": null
                                },
                                "command.stderr.split": {
                                    "variable_value": "None",
                                    "variable_type": "NoneType",
                                    "variable_shape": null
                                },
                                "command.stderr": {
                                    "variable_value": "'fatal: The current branch master has no upstream branch.\\nTo push the current branch and set the remote as upstream, use\\n\\n    git push --set-upstream origin master\\n\\n'",
                                    "variable_type": "str",
                                    "variable_shape": "164"
                                },
                                "replace_argument": {
                                    "variable_value": null,
                                    "variable_type": "None",
                                    "variable_shape": null
                                },
                                "join": {
                                    "variable_value": null,
                                    "variable_type": "None",
                                    "variable_shape": null
                                },
                                "git_support": {
                                    "variable_value": null,
                                    "variable_type": "None",
                                    "variable_shape": null
                                }
                            }
                        ],
                        [
                            {
                                "upstream_option_index": {
                                    "variable_value": null,
                                    "variable_type": "None",
                                    "variable_shape": null
                                },
                                "command.script_parts.index": {
                                    "variable_value": "None",
                                    "variable_type": "NoneType",
                                    "variable_shape": null
                                },
                                "command.script_parts": {
                                    "variable_value": "['git', 'push', '--set-upstream', 'origin']",
                                    "variable_type": "list",
                                    "variable_shape": "4"
                                },
                                "command": {
                                    "variable_value": "Command(script=git push --set-upstream origin, stdout=, stderr=fatal: The current branch master has no upstream branch.\nTo push the current branch and set the remote as upstream, use\n\n    git push --set-upstream origin master\n\n)",
                                    "variable_type": "Command",
                                    "variable_shape": null
                                },
                                "command.script_parts.pop": {
                                    "variable_value": "None",
                                    "variable_type": "NoneType",
                                    "variable_shape": null
                                },
                                "push_upstream": {
                                    "variable_value": null,
                                    "variable_type": "None",
                                    "variable_shape": null
                                },
                                "partition": {
                                    "variable_value": null,
                                    "variable_type": "None",
                                    "variable_shape": null
                                },
                                "strip": {
                                    "variable_value": null,
                                    "variable_type": "None",
                                    "variable_shape": null
                                },
                                "command.stderr.split": {
                                    "variable_value": "None",
                                    "variable_type": "NoneType",
                                    "variable_shape": null
                                },
                                "command.stderr": {
                                    "variable_value": "'fatal: The current branch master has no upstream branch.\\nTo push the current branch and set the remote as upstream, use\\n\\n    git push --set-upstream origin master\\n\\n'",
                                    "variable_type": "str",
                                    "variable_shape": "164"
                                },
                                "replace_argument": {
                                    "variable_value": null,
                                    "variable_type": "None",
                                    "variable_shape": null
                                },
                                "join": {
                                    "variable_value": null,
                                    "variable_type": "None",
                                    "variable_shape": null
                                },
                                "git_support": {
                                    "variable_value": null,
                                    "variable_type": "None",
                                    "variable_shape": null
                                }
                            },
                            {
                                "upstream_option_index": {
                                    "variable_value": "2",
                                    "variable_type": "int",
                                    "variable_shape": null
                                },
                                "command.script_parts.index": {
                                    "variable_value": "None",
                                    "variable_type": "NoneType",
                                    "variable_shape": null
                                },
                                "command.script_parts": {
                                    "variable_value": "['git', 'push']",
                                    "variable_type": "list",
                                    "variable_shape": "2"
                                },
                                "command": {
                                    "variable_value": "Command(script=git push --set-upstream origin, stdout=, stderr=fatal: The current branch master has no upstream branch.\nTo push the current branch and set the remote as upstream, use\n\n    git push --set-upstream origin master\n\n)",
                                    "variable_type": "Command",
                                    "variable_shape": null
                                },
                                "command.script_parts.pop": {
                                    "variable_value": "None",
                                    "variable_type": "NoneType",
                                    "variable_shape": null
                                },
                                "push_upstream": {
                                    "variable_value": "'push --set-upstream origin master'",
                                    "variable_type": "str",
                                    "variable_shape": "33"
                                },
                                "partition": {
                                    "variable_value": null,
                                    "variable_type": "None",
                                    "variable_shape": null
                                },
                                "strip": {
                                    "variable_value": null,
                                    "variable_type": "None",
                                    "variable_shape": null
                                },
                                "command.stderr.split": {
                                    "variable_value": "None",
                                    "variable_type": "NoneType",
                                    "variable_shape": null
                                },
                                "command.stderr": {
                                    "variable_value": "'fatal: The current branch master has no upstream branch.\\nTo push the current branch and set the remote as upstream, use\\n\\n    git push --set-upstream origin master\\n\\n'",
                                    "variable_type": "str",
                                    "variable_shape": "164"
                                },
                                "replace_argument": {
                                    "variable_value": null,
                                    "variable_type": "None",
                                    "variable_shape": null
                                },
                                "join": {
                                    "variable_value": null,
                                    "variable_type": "None",
                                    "variable_shape": null
                                },
                                "git_support": {
                                    "variable_value": null,
                                    "variable_type": "None",
                                    "variable_shape": null
                                }
                            }
                        ],
                        [
                            {
                                "upstream_option_index": {
                                    "variable_value": null,
                                    "variable_type": "None",
                                    "variable_shape": null
                                },
                                "command.script_parts.index": {
                                    "variable_value": "None",
                                    "variable_type": "NoneType",
                                    "variable_shape": null
                                },
                                "command.script_parts": {
                                    "variable_value": "['git', 'push', '--quiet']",
                                    "variable_type": "list",
                                    "variable_shape": "3"
                                },
                                "command": {
                                    "variable_value": "Command(script=git push --quiet, stdout=, stderr=fatal: The current branch master has no upstream branch.\nTo push the current branch and set the remote as upstream, use\n\n    git push --set-upstream origin master\n\n)",
                                    "variable_type": "Command",
                                    "variable_shape": null
                                },
                                "command.script_parts.pop": {
                                    "variable_value": "None",
                                    "variable_type": "NoneType",
                                    "variable_shape": null
                                },
                                "push_upstream": {
                                    "variable_value": null,
                                    "variable_type": "None",
                                    "variable_shape": null
                                },
                                "partition": {
                                    "variable_value": null,
                                    "variable_type": "None",
                                    "variable_shape": null
                                },
                                "strip": {
                                    "variable_value": null,
                                    "variable_type": "None",
                                    "variable_shape": null
                                },
                                "command.stderr.split": {
                                    "variable_value": "None",
                                    "variable_type": "NoneType",
                                    "variable_shape": null
                                },
                                "command.stderr": {
                                    "variable_value": "'fatal: The current branch master has no upstream branch.\\nTo push the current branch and set the remote as upstream, use\\n\\n    git push --set-upstream origin master\\n\\n'",
                                    "variable_type": "str",
                                    "variable_shape": "164"
                                },
                                "replace_argument": {
                                    "variable_value": null,
                                    "variable_type": "None",
                                    "variable_shape": null
                                },
                                "join": {
                                    "variable_value": null,
                                    "variable_type": "None",
                                    "variable_shape": null
                                },
                                "git_support": {
                                    "variable_value": null,
                                    "variable_type": "None",
                                    "variable_shape": null
                                }
                            },
                            {
                                "upstream_option_index": {
                                    "variable_value": "-1",
                                    "variable_type": "int",
                                    "variable_shape": null
                                },
                                "command.script_parts.index": {
                                    "variable_value": "None",
                                    "variable_type": "NoneType",
                                    "variable_shape": null
                                },
                                "command.script_parts": {
                                    "variable_value": "['git', 'push', '--quiet']",
                                    "variable_type": "list",
                                    "variable_shape": "3"
                                },
                                "command": {
                                    "variable_value": "Command(script=git push --quiet, stdout=, stderr=fatal: The current branch master has no upstream branch.\nTo push the current branch and set the remote as upstream, use\n\n    git push --set-upstream origin master\n\n)",
                                    "variable_type": "Command",
                                    "variable_shape": null
                                },
                                "command.script_parts.pop": {
                                    "variable_value": "None",
                                    "variable_type": "NoneType",
                                    "variable_shape": null
                                },
                                "push_upstream": {
                                    "variable_value": "'push --set-upstream origin master'",
                                    "variable_type": "str",
                                    "variable_shape": "33"
                                },
                                "partition": {
                                    "variable_value": null,
                                    "variable_type": "None",
                                    "variable_shape": null
                                },
                                "strip": {
                                    "variable_value": null,
                                    "variable_type": "None",
                                    "variable_shape": null
                                },
                                "command.stderr.split": {
                                    "variable_value": "None",
                                    "variable_type": "NoneType",
                                    "variable_shape": null
                                },
                                "command.stderr": {
                                    "variable_value": "'fatal: The current branch master has no upstream branch.\\nTo push the current branch and set the remote as upstream, use\\n\\n    git push --set-upstream origin master\\n\\n'",
                                    "variable_type": "str",
                                    "variable_shape": "164"
                                },
                                "replace_argument": {
                                    "variable_value": null,
                                    "variable_type": "None",
                                    "variable_shape": null
                                },
                                "join": {
                                    "variable_value": null,
                                    "variable_type": "None",
                                    "variable_shape": null
                                },
                                "git_support": {
                                    "variable_value": null,
                                    "variable_type": "None",
                                    "variable_shape": null
                                }
                            }
                        ]
                    ]
                }
            ],
            "inscope_functions": [
                "@git_support\ndef match(command):\n    return ('push' in command.script\n            and 'set-upstream' in command.stderr)",
                "@git_support\ndef get_new_command(command):\n    # If --set-upstream or -u are passed, remove it and its argument. This is\n    # because the remaining arguments are concatenated onto the command suggested\n    # by git, which includes --set-upstream and its argument\n    upstream_option_index = -1\n    try:\n        upstream_option_index = command.script_parts.index('--set-upstream')\n    except ValueError:\n        pass\n    try:\n        upstream_option_index = command.script_parts.index('-u')\n    except ValueError:\n        pass\n    if upstream_option_index is not -1:\n        command.script_parts.pop(upstream_option_index)\n        command.script_parts.pop(upstream_option_index)\n\n    push_upstream = command.stderr.split('\\n')[-3].strip().partition('git ')[2]\n    return replace_argument(\" \".join(command.script_parts), 'push', push_upstream)"
            ],
            "inscope_function_signatures": [
                "match(command)",
                "get_new_command(command)"
            ],
            "variables_in_file": {
                "command.script": [
                    7
                ],
                "command": [
                    7,
                    8,
                    18,
                    22,
                    26,
                    27,
                    29,
                    30
                ],
                "command.stderr": [
                    8,
                    29
                ],
                "git_support": [
                    11,
                    5
                ],
                "upstream_option_index": [
                    16,
                    18,
                    22,
                    25,
                    26,
                    27
                ],
                "command.script_parts.index": [
                    18,
                    22
                ],
                "command.script_parts": [
                    18,
                    22,
                    26,
                    27,
                    30
                ],
                "ValueError": [
                    19,
                    23
                ],
                "command.script_parts.pop": [
                    26,
                    27
                ],
                "push_upstream": [
                    29,
                    30
                ],
                "partition": [
                    29
                ],
                "strip": [
                    29
                ],
                "command.stderr.split": [
                    29
                ],
                "replace_argument": [
                    30
                ],
                "join": [
                    30
                ]
            },
            "filtered_variables_in_file": {
                "command.script": [
                    7
                ],
                "command": [
                    7,
                    8,
                    18,
                    22,
                    26,
                    27,
                    29,
                    30
                ],
                "command.stderr": [
                    8,
                    29
                ],
                "git_support": [
                    11,
                    5
                ],
                "upstream_option_index": [
                    16,
                    18,
                    22,
                    25,
                    26,
                    27
                ],
                "command.script_parts.index": [
                    18,
                    22
                ],
                "command.script_parts": [
                    18,
                    22,
                    26,
                    27,
                    30
                ],
                "command.script_parts.pop": [
                    26,
                    27
                ],
                "push_upstream": [
                    29,
                    30
                ],
                "partition": [
                    29
                ],
                "strip": [
                    29
                ],
                "command.stderr.split": [
                    29
                ],
                "replace_argument": [
                    30
                ],
                "join": [
                    30
                ]
            }
        },
        "test_data": [
            {
                "test_path": "/Volumes/SSD2T/bgp_envs_non_pandas/repos/thefuck_9/tests/rules/test_git_push.py",
                "test_function": "test_get_new_command",
                "test_function_code": "def test_get_new_command(stderr):\n    assert get_new_command(Command('git push', stderr=stderr))\\\n        == \"git push --set-upstream origin master\"\n    assert get_new_command(Command('git push -u', stderr=stderr))\\\n        == \"git push --set-upstream origin master\"\n    assert get_new_command(Command('git push -u origin', stderr=stderr))\\\n        == \"git push --set-upstream origin master\"\n    assert get_new_command(Command('git push --set-upstream origin', stderr=stderr))\\\n        == \"git push --set-upstream origin master\"\n    assert get_new_command(Command('git push --quiet', stderr=stderr))\\\n        == \"git push --set-upstream origin master --quiet\"",
                "test_error": "IndexError: pop index out of range",
                "full_test_error": "stderr = 'fatal: The current branch master has no upstream branch.\\nTo push the current branch and set the remote as upstream, use\\n\\n    git push --set-upstream origin master\\n\\n'\n\n    def test_get_new_command(stderr):\n        assert get_new_command(Command('git push', stderr=stderr))\\\n            == \"git push --set-upstream origin master\"\n>       assert get_new_command(Command('git push -u', stderr=stderr))\\\n            == \"git push --set-upstream origin master\"\n\ntests/rules/test_git_push.py:26: \n_ _ _ _ _ _ _ _ _ _ _ _ _ _ _ _ _ _ _ _ _ _ _ _ _ _ _ _ _ _ _ _ _ _ _ _ _ _ _ _ \n<decorator-gen-7>:2: in get_new_command\n    ???\nthefuck/specific/git.py:32: in git_support\n    return fn(command)\n_ _ _ _ _ _ _ _ _ _ _ _ _ _ _ _ _ _ _ _ _ _ _ _ _ _ _ _ _ _ _ _ _ _ _ _ _ _ _ _ \n\ncommand = Command(script=git push -u, stdout=, stderr=fatal: The current branch master has no upstream branch.\nTo push the current branch and set the remote as upstream, use\n\n    git push --set-upstream origin master\n\n)\n\n    @git_support\n    def get_new_command(command):\n        # If --set-upstream or -u are passed, remove it and its argument. This is\n        # because the remaining arguments are concatenated onto the command suggested\n        # by git, which includes --set-upstream and its argument\n        upstream_option_index = -1\n        try:\n            upstream_option_index = command.script_parts.index('--set-upstream')\n        except ValueError:\n            pass\n        try:\n            upstream_option_index = command.script_parts.index('-u')\n        except ValueError:\n            pass\n        if upstream_option_index is not -1:\n            command.script_parts.pop(upstream_option_index)\n>           command.script_parts.pop(upstream_option_index)\nE           IndexError: pop index out of range\n\nthefuck/rules/git_push.py:27: IndexError",
                "traceback": "<decorator-gen-7>:2: in get_new_command\n    ???\nthefuck/specific/git.py:32: in git_support\n    return fn(command)",
                "test_error_location": "_ _ _ _ _ _ _ _ _ _ _ _ _ _ _ _ _ _ _ _ _ _ _ _ _ _ _ _ _ _ _ _ _ _ _ _ _ _ _ _ \n\ncommand = Command(script=git push -u, stdout=, stderr=fatal: The current branch master has no upstream branch.\nTo push the current branch and set the remote as upstream, use\n\n    git push --set-upstream origin master\n\n)\n\n    @git_support\n    def get_new_command(command):\n        # If --set-upstream or -u are passed, remove it and its argument. This is\n        # because the remaining arguments are concatenated onto the command suggested\n        # by git, which includes --set-upstream and its argument\n        upstream_option_index = -1\n        try:\n            upstream_option_index = command.script_parts.index('--set-upstream')\n        except ValueError:\n            pass\n        try:\n            upstream_option_index = command.script_parts.index('-u')\n        except ValueError:\n            pass\n        if upstream_option_index is not -1:\n            command.script_parts.pop(upstream_option_index)\n>           command.script_parts.pop(upstream_option_index)\nE           IndexError: pop index out of range\n\nthefuck/rules/git_push.py:27: IndexError",
                "test_function_decorators": []
            }
        ]
    }
}